MANIFEST.in
README.md
setup.py
Octoprint_Addlink.egg-info/PKG-INFO
Octoprint_Addlink.egg-info/SOURCES.txt
Octoprint_Addlink.egg-info/dependency_links.txt
Octoprint_Addlink.egg-info/entry_points.txt
Octoprint_Addlink.egg-info/not-zip-safe
Octoprint_Addlink.egg-info/requires.txt
Octoprint_Addlink.egg-info/top_level.txt
octoprint_addlink/__init__.py
octoprint_addlink/static/css/addlink.css
octoprint_addlink/static/img/logo.png
octoprint_addlink/static/js/addlink.js
octoprint_addlink/static/less/addlink.less
octoprint_addlink/templates/README.txt
octoprint_addlink/templates/addlink_navbar.jinja2
octoprint_addlink/templates/addlink_tab.jinja2