Metadata-Version: 1.0
Name: Octoprint-Addlink
Version: 0.0.1
Summary: Connect Octoprint with addlink
Home-page: https://github.com/addnorth/Octoprint-Addlink
Author: Carl-Fredrik Hårsmar
Author-email: carl-fredrik@addnorth.com
License: AGPLv3
Platform: UNKNOWN
